msgpack_lz4block/__init__.py
tests/__init__.py
tests/test_functions.py
msgpack_lz4block-0.2.6.dist-info/LICENSE.txt
msgpack_lz4block-0.2.6.dist-info/METADATA
msgpack_lz4block-0.2.6.dist-info/WHEEL
msgpack_lz4block-0.2.6.dist-info/top_level.txt
msgpack_lz4block-0.2.6.dist-info/RECORD
